torchember/__init__.py
torchember/_nbdev.py
torchember/config.py
torchember/core.py
torchember/fastai.py
torchember/helper.py
torchember/run.py
torchember/utils.py
torchember/visual.py
torchember/whyhat.py
torchember/app/__init__.py
torchember/app/models.py
torchember/app/static/appbuilder/css/ab.css
torchember/app/static/appbuilder/css/bootstrap.min.css
torchember/app/static/appbuilder/css/font-awesome.min.css
torchember/app/static/appbuilder/css/flags/flags16.css
torchember/app/static/appbuilder/css/themes/amelia.css
torchember/app/static/appbuilder/css/themes/cerulean.css
torchember/app/static/appbuilder/css/themes/cosmo.css
torchember/app/static/appbuilder/css/themes/cyborg.css
torchember/app/static/appbuilder/css/themes/darkly.css
torchember/app/static/appbuilder/css/themes/flatly.css
torchember/app/static/appbuilder/css/themes/journal.css
torchember/app/static/appbuilder/css/themes/lumen.css
torchember/app/static/appbuilder/css/themes/paper.css
torchember/app/static/appbuilder/css/themes/readable.css
torchember/app/static/appbuilder/css/themes/sandstone.css
torchember/app/static/appbuilder/css/themes/simplex.css
torchember/app/static/appbuilder/css/themes/slate.css
torchember/app/static/appbuilder/css/themes/solar.css
torchember/app/static/appbuilder/css/themes/spacelab.css
torchember/app/static/appbuilder/css/themes/superhero.css
torchember/app/static/appbuilder/css/themes/united.css
torchember/app/static/appbuilder/css/themes/yeti.css
torchember/app/static/appbuilder/datepicker/bootstrap-datepicker.css
torchember/app/static/appbuilder/datepicker/bootstrap-datepicker.js
torchember/app/static/appbuilder/fonts/FontAwesome.otf
torchember/app/static/appbuilder/fonts/fontawesome-webfont.eot
torchember/app/static/appbuilder/fonts/fontawesome-webfont.svg
torchember/app/static/appbuilder/fonts/fontawesome-webfont.ttf
torchember/app/static/appbuilder/fonts/fontawesome-webfont.woff
torchember/app/static/appbuilder/fonts/fontawesome-webfont.woff2
torchember-0.2.7.dist-info/LICENSE
torchember-0.2.7.dist-info/METADATA
torchember-0.2.7.dist-info/WHEEL
torchember-0.2.7.dist-info/entry_points.txt
torchember-0.2.7.dist-info/top_level.txt
torchember-0.2.7.dist-info/RECORD
